auth/constants.py
auth/rhoas_auth.py
rhoas_connector_mgmt_sdk/__init__.py
rhoas_connector_mgmt_sdk/api/__init__.py
rhoas_connector_mgmt_sdk/api/connector_clusters_api.py
rhoas_connector_mgmt_sdk/api/connector_namespaces_api.py
rhoas_connector_mgmt_sdk/api/connector_service_api.py
rhoas_connector_mgmt_sdk/api/connector_types_api.py
rhoas_connector_mgmt_sdk/api/connectors_api.py
rhoas_connector_mgmt_sdk/api_client.py
rhoas_connector_mgmt_sdk/apis/__init__.py
rhoas_connector_mgmt_sdk/configuration.py
rhoas_connector_mgmt_sdk/exceptions.py
rhoas_connector_mgmt_sdk/model/__init__.py
rhoas_connector_mgmt_sdk/model/addon_parameter.py
rhoas_connector_mgmt_sdk/model/addon_parameter_list.py
rhoas_connector_mgmt_sdk/model/channel.py
rhoas_connector_mgmt_sdk/model/connector.py
rhoas_connector_mgmt_sdk/model/connector_cluster.py
rhoas_connector_mgmt_sdk/model/connector_cluster_list.py
rhoas_connector_mgmt_sdk/model/connector_cluster_list_all_of.py
rhoas_connector_mgmt_sdk/model/connector_cluster_meta.py
rhoas_connector_mgmt_sdk/model/connector_cluster_request.py
rhoas_connector_mgmt_sdk/model/connector_cluster_request_meta.py
rhoas_connector_mgmt_sdk/model/connector_cluster_state.py
rhoas_connector_mgmt_sdk/model/connector_cluster_status.py
rhoas_connector_mgmt_sdk/model/connector_cluster_status_status.py
rhoas_connector_mgmt_sdk/model/connector_configuration.py
rhoas_connector_mgmt_sdk/model/connector_desired_state.py
rhoas_connector_mgmt_sdk/model/connector_list.py
rhoas_connector_mgmt_sdk/model/connector_list_all_of.py
rhoas_connector_mgmt_sdk/model/connector_meta.py
rhoas_connector_mgmt_sdk/model/connector_meta_all_of.py
rhoas_connector_mgmt_sdk/model/connector_namespace.py
rhoas_connector_mgmt_sdk/model/connector_namespace_all_of.py
rhoas_connector_mgmt_sdk/model/connector_namespace_eval_request.py
rhoas_connector_mgmt_sdk/model/connector_namespace_list.py
rhoas_connector_mgmt_sdk/model/connector_namespace_list_all_of.py
rhoas_sdks-1.0.5.dist-info/METADATA
rhoas_sdks-1.0.5.dist-info/WHEEL
rhoas_sdks-1.0.5.dist-info/RECORD
