Metadata-Version: 2.1
Name: rhoas-sdks
Version: 1.0.5
Summary: A package which includes RHOAS SDKs
License: Apache License
Author: dimakis
Author-email: dsaridak@redhat.com
Requires-Python: >=3.9,<4.0
Classifier: License :: Other/Proprietary License
Classifier: Programming Language :: Python :: 3
Classifier: Programming Language :: Python :: 3.9
Classifier: Programming Language :: Python :: 3.10
Classifier: Programming Language :: Python :: 3.11
Requires-Dist: python-dateutil
Requires-Dist: python-keycloak (>=2.5.0,<3.0.0)
Requires-Dist: urllib3 (>=1.25.3,<2.0.0)
